pydqm-0.1.3.dist-info/WHEEL
pydqm-0.1.3.dist-info/METADATA
pydqm-0.1.3.dist-info/RECORD
pydqm-0.1.3.dist-info/licenses/LICENSE.txt
dqm/dqm_pure_python.py
dqm/utils.py
dqm/DQMTests.py
dqm/.ruff.toml
dqm/UtilTests.py
dqm/__init__.py
dqm/DQM.py
dqm/bin/dqm_python.so
pydqm.libs/libgomp-a34b3233.so.1.0.0
