Metadata-Version: 2.2
Name: pydqm
Version: 0.1.3
Summary: Dynamic Quantum Mapping
Keywords: dimensionality reduction,visualization,animation,data science
Author-Email: Zander Teller <zander.teller@gmail.com>
License: MIT License
Classifier: Development Status :: 4 - Beta
Classifier: Intended Audience :: Science/Research
Classifier: License :: OSI Approved :: MIT License
Classifier: Operating System :: MacOS
Classifier: Operating System :: POSIX :: Linux
Classifier: Programming Language :: Python :: 3
Classifier: Programming Language :: Python :: 3.10
Classifier: Programming Language :: Python :: 3.11
Classifier: Programming Language :: Python :: 3.12
Classifier: Programming Language :: Python :: 3.13
Classifier: Programming Language :: C++
Classifier: Topic :: Scientific/Engineering
Project-URL: Homepage, https://github.com/zanderteller/dqm
Project-URL: Documentation, https://dqm.readthedocs.io
Project-URL: Repository, https://github.com/zanderteller/dqm
Project-URL: Issues, https://github.com/zanderteller/dqm/issues
Project-URL: Changelog, https://github.com/zanderteller/dqm/releases
Requires-Python: >=3.10
Requires-Dist: numpy
Provides-Extra: viz
Requires-Dist: jupyterlab; extra == "viz"
Requires-Dist: plotly; extra == "viz"
Requires-Dist: matplotlib; extra == "viz"
Provides-Extra: dev
Requires-Dist: pytest; extra == "dev"
Requires-Dist: ruff; extra == "dev"
